llama_index/storage/chat_store/upstash/__init__.py
llama_index/storage/chat_store/upstash/base.py
llama_index_storage_chat_store_upstash-0.3.1.dist-info/METADATA
llama_index_storage_chat_store_upstash-0.3.1.dist-info/WHEEL
llama_index_storage_chat_store_upstash-0.3.1.dist-info/licenses/LICENSE
llama_index_storage_chat_store_upstash-0.3.1.dist-info/RECORD
