Metadata-Version: 2.4
Name: llama-index-storage-chat-store-upstash
Version: 0.3.1
Summary: llama-index storage-chat-store upstash integration
Author-email: Fahreddin Özcan <fahreddin@upstash.com>
License-Expression: MIT
License-File: LICENSE
Requires-Python: <4.0,>=3.9
Requires-Dist: llama-index-core<0.15,>=0.13.0
Requires-Dist: upstash-redis<2,>=1.1.0
